{"id":157,"name":"BHUVANAGIRI","district":"Nagapattinam","candidates":[{"rank":1,"name":"ARUNMOZHITHEVAN . A","party":"AIADMK","evmVotes":74628,"postalVotes":1079,"totalVotes":75707,"percentage":36.52,"isLeading":true},{"rank":2,"name":"SARAVANAN. DURAI . K","party":"DMK","evmVotes":72220,"postalVotes":1000,"totalVotes":73220,"percentage":35.32,"isLeading":false},{"rank":3,"name":"MAHALINGAM . T","party":"TVK","evmVotes":49506,"postalVotes":398,"totalVotes":49904,"percentage":24.07,"isLeading":false},{"rank":4,"name":"SUMATHI . S","party":"NTK","evmVotes":5025,"postalVotes":80,"totalVotes":5105,"percentage":2.46,"isLeading":false},{"rank":5,"name":"MUTHAMIZHAN . SEVA","party":"TVK","evmVotes":894,"postalVotes":18,"totalVotes":912,"percentage":0.44,"isLeading":false},{"rank":6,"name":"NOTA","party":"NOTA","evmVotes":672,"postalVotes":9,"totalVotes":681,"percentage":0.33,"isLeading":false},{"rank":7,"name":"KUMARAVELU . M","party":"BSP","evmVotes":360,"postalVotes":3,"totalVotes":363,"percentage":0.18,"isLeading":false},{"rank":8,"name":"BALAMURUGAN . G. C","party":"IND","evmVotes":336,"postalVotes":3,"totalVotes":339,"percentage":0.16,"isLeading":false},{"rank":9,"name":"BALAMURUGAN . M. R","party":"IND","evmVotes":324,"postalVotes":0,"totalVotes":324,"percentage":0.16,"isLeading":false},{"rank":10,"name":"ARUNMOZHI . V","party":"IND","evmVotes":306,"postalVotes":2,"totalVotes":308,"percentage":0.15,"isLeading":false},{"rank":11,"name":"RAJA SEKAR . G","party":"IND","evmVotes":239,"postalVotes":0,"totalVotes":239,"percentage":0.12,"isLeading":false},{"rank":12,"name":"SARAVANAN . J","party":"IND","evmVotes":83,"postalVotes":6,"totalVotes":89,"percentage":0.04,"isLeading":false},{"rank":13,"name":"IYYAPPAN . S","party":"IND","evmVotes":69,"postalVotes":1,"totalVotes":70,"percentage":0.03,"isLeading":false},{"rank":14,"name":"EZHILVENTHAN . P","party":"IND","evmVotes":48,"postalVotes":1,"totalVotes":49,"percentage":0.02,"isLeading":false}],"totalVotesCounted":207310,"round":"","lastUpdated":"at 11:39 PM On 04/05/2026"}