{"id":66,"name":"POLUR","district":"Villupuram","candidates":[{"rank":1,"name":"ABISHEK. R","party":"TVK","evmVotes":54899,"postalVotes":0,"totalVotes":54899,"percentage":32.72,"isLeading":true},{"rank":2,"name":"SARAVANAN. P","party":"DMDK","evmVotes":53955,"postalVotes":0,"totalVotes":53955,"percentage":32.16,"isLeading":false},{"rank":3,"name":"BASKARAN. C. R","party":"PMK","evmVotes":47455,"postalVotes":0,"totalVotes":47455,"percentage":28.29,"isLeading":false},{"rank":4,"name":"UMADEVI. A","party":"NTK","evmVotes":5041,"postalVotes":0,"totalVotes":5041,"percentage":3,"isLeading":false},{"rank":5,"name":"PURUSOTHAMAN. M","party":"IND","evmVotes":1274,"postalVotes":0,"totalVotes":1274,"percentage":0.76,"isLeading":false},{"rank":6,"name":"DHAVAMANI. P","party":"ACDP","evmVotes":1045,"postalVotes":0,"totalVotes":1045,"percentage":0.62,"isLeading":false},{"rank":7,"name":"SHANMUGAVELU. A","party":"VTVTK","evmVotes":781,"postalVotes":0,"totalVotes":781,"percentage":0.47,"isLeading":false},{"rank":8,"name":"BASKARAN. C","party":"IND","evmVotes":724,"postalVotes":0,"totalVotes":724,"percentage":0.43,"isLeading":false},{"rank":9,"name":"BANUPRIYA. D","party":"RPOI(","evmVotes":680,"postalVotes":0,"totalVotes":680,"percentage":0.41,"isLeading":false},{"rank":10,"name":"NOTA","party":"NOTA","evmVotes":644,"postalVotes":0,"totalVotes":644,"percentage":0.38,"isLeading":false},{"rank":11,"name":"SUBHA. A","party":"IND","evmVotes":348,"postalVotes":0,"totalVotes":348,"percentage":0.21,"isLeading":false},{"rank":12,"name":"SARAVANAN. P","party":"IND","evmVotes":263,"postalVotes":0,"totalVotes":263,"percentage":0.16,"isLeading":false},{"rank":13,"name":"MANIKANDAN. R","party":"AJPK","evmVotes":233,"postalVotes":0,"totalVotes":233,"percentage":0.14,"isLeading":false},{"rank":14,"name":"SYED MUKRAM. R. N","party":"TVK","evmVotes":197,"postalVotes":0,"totalVotes":197,"percentage":0.12,"isLeading":false},{"rank":15,"name":"EZHIL ARASU. M M.A. L.L.M.","party":"IND","evmVotes":128,"postalVotes":0,"totalVotes":128,"percentage":0.08,"isLeading":false},{"rank":16,"name":"SARAVANAN. M","party":"IND","evmVotes":107,"postalVotes":0,"totalVotes":107,"percentage":0.06,"isLeading":false}],"totalVotesCounted":167774,"round":"","lastUpdated":"at 08:57 PM On 04/05/2026"}