{"id":68,"name":"CHEYYAR","district":"Villupuram","candidates":[{"rank":1,"name":"MUKKUR N. SUBRAMANIAN","party":"AIADMK","evmVotes":85939,"postalVotes":741,"totalVotes":86680,"percentage":38.95,"isLeading":true},{"rank":2,"name":"DUSI K MOHAN","party":"TVK","evmVotes":65217,"postalVotes":382,"totalVotes":65599,"percentage":29.47,"isLeading":false},{"rank":3,"name":"JOTHI. O","party":"DMK","evmVotes":59231,"postalVotes":663,"totalVotes":59894,"percentage":26.91,"isLeading":false},{"rank":4,"name":"TAMILSELVAN. M","party":"NTK","evmVotes":6941,"postalVotes":102,"totalVotes":7043,"percentage":3.16,"isLeading":false},{"rank":5,"name":"NOTA","party":"NOTA","evmVotes":939,"postalVotes":11,"totalVotes":950,"percentage":0.43,"isLeading":false},{"rank":6,"name":"KUTTIMANI. S","party":"VTVTK","evmVotes":397,"postalVotes":4,"totalVotes":401,"percentage":0.18,"isLeading":false},{"rank":7,"name":"MOHAN. R","party":"IND","evmVotes":394,"postalVotes":0,"totalVotes":394,"percentage":0.18,"isLeading":false},{"rank":8,"name":"DURUGAN. M","party":"VBA","evmVotes":333,"postalVotes":1,"totalVotes":334,"percentage":0.15,"isLeading":false},{"rank":9,"name":"ARJUNAN. M","party":"IND","evmVotes":320,"postalVotes":0,"totalVotes":320,"percentage":0.14,"isLeading":false},{"rank":10,"name":"SRINIVASAN. K","party":"AJPK","evmVotes":257,"postalVotes":2,"totalVotes":259,"percentage":0.12,"isLeading":false},{"rank":11,"name":"VENKATESAN. V","party":"ASMK","evmVotes":224,"postalVotes":0,"totalVotes":224,"percentage":0.1,"isLeading":false},{"rank":12,"name":"PALANI. M","party":"TVK","evmVotes":159,"postalVotes":23,"totalVotes":182,"percentage":0.08,"isLeading":false},{"rank":13,"name":"CHANDRASEKARAN. M","party":"AIJMK","evmVotes":143,"postalVotes":2,"totalVotes":145,"percentage":0.07,"isLeading":false},{"rank":14,"name":"RAGUPATHI. S","party":"ACDP","evmVotes":124,"postalVotes":21,"totalVotes":145,"percentage":0.07,"isLeading":false}],"totalVotesCounted":222570,"round":"","lastUpdated":"at 10:45 PM On 04/05/2026"}