{"id":73,"name":"VANUR","district":"Kallakurichi","candidates":[{"rank":1,"name":"GOWTHAM D","party":"DMK","evmVotes":68418,"postalVotes":455,"totalVotes":68873,"percentage":35.85,"isLeading":true},{"rank":2,"name":"SURESH P","party":"TVK","evmVotes":61589,"postalVotes":250,"totalVotes":61839,"percentage":32.19,"isLeading":false},{"rank":3,"name":"MURUGAN P","party":"AIADMK","evmVotes":53839,"postalVotes":354,"totalVotes":54193,"percentage":28.21,"isLeading":false},{"rank":4,"name":"KARIKALAN B","party":"NTK","evmVotes":4654,"postalVotes":43,"totalVotes":4697,"percentage":2.44,"isLeading":false},{"rank":5,"name":"VETRIVEL G","party":"IND","evmVotes":571,"postalVotes":1,"totalVotes":572,"percentage":0.3,"isLeading":false},{"rank":6,"name":"NOTA","party":"NOTA","evmVotes":510,"postalVotes":9,"totalVotes":519,"percentage":0.27,"isLeading":false},{"rank":7,"name":"SAKTHIVEL S","party":"TVK","evmVotes":283,"postalVotes":2,"totalVotes":285,"percentage":0.15,"isLeading":false},{"rank":8,"name":"VINAYAGAMOORTHY M","party":"BSP","evmVotes":265,"postalVotes":0,"totalVotes":265,"percentage":0.14,"isLeading":false},{"rank":9,"name":"RADHIKA S","party":"IND","evmVotes":197,"postalVotes":0,"totalVotes":197,"percentage":0.1,"isLeading":false},{"rank":10,"name":"SATHYARAMAN P","party":"IND","evmVotes":172,"postalVotes":0,"totalVotes":172,"percentage":0.09,"isLeading":false},{"rank":11,"name":"SIVAKUMAR R","party":"IND","evmVotes":111,"postalVotes":1,"totalVotes":112,"percentage":0.06,"isLeading":false},{"rank":12,"name":"ANANDAKUMAR P M","party":"TK","evmVotes":95,"postalVotes":0,"totalVotes":95,"percentage":0.05,"isLeading":false},{"rank":13,"name":"AYYANAR E","party":"IND","evmVotes":93,"postalVotes":0,"totalVotes":93,"percentage":0.05,"isLeading":false},{"rank":14,"name":"MURALI M","party":"IND","evmVotes":83,"postalVotes":0,"totalVotes":83,"percentage":0.04,"isLeading":false},{"rank":15,"name":"SURESH C V","party":"IND","evmVotes":67,"postalVotes":1,"totalVotes":68,"percentage":0.04,"isLeading":false},{"rank":16,"name":"THANGARASU N","party":"IND","evmVotes":56,"postalVotes":0,"totalVotes":56,"percentage":0.03,"isLeading":false}],"totalVotesCounted":192119,"round":"","lastUpdated":"at 10:45 PM On 04/05/2026"}