{"id":114,"name":"KONNI","district":"Kannur","candidates":[{"rank":1,"name":"ADV K U JENISH KUMAR","party":"CPI(M)","evmVotes":59255,"postalVotes":1125,"totalVotes":60380,"percentage":44.59,"isLeading":true},{"rank":2,"name":"PROF SATHEESH KOCHUPARAMBIL","party":"INC","evmVotes":57186,"postalVotes":1356,"totalVotes":58542,"percentage":43.23,"isLeading":false},{"rank":3,"name":"SUNDARESAN T P","party":"BDJS","evmVotes":14992,"postalVotes":286,"totalVotes":15278,"percentage":11.28,"isLeading":false},{"rank":4,"name":"NOTA","party":"NOTA","evmVotes":788,"postalVotes":17,"totalVotes":805,"percentage":0.59,"isLeading":false},{"rank":5,"name":"ADV VARUGHESE OOMMEN","party":"IND","evmVotes":384,"postalVotes":16,"totalVotes":400,"percentage":0.3,"isLeading":false}],"totalVotesCounted":135405,"round":"","lastUpdated":"at 12:42 AM On 05/05/2026"}