{"id":62,"name":"KUNNAMKULAM","district":"Ernakulam","candidates":[{"rank":1,"name":"A C MOIDEEN","party":"CPI(M)","evmVotes":68693,"postalVotes":829,"totalVotes":69522,"percentage":45.22,"isLeading":true},{"rank":2,"name":"P T AJAY MOHAN","party":"INC","evmVotes":64008,"postalVotes":951,"totalVotes":64959,"percentage":42.25,"isLeading":false},{"rank":3,"name":"K R RAJIN","party":"BDJS","evmVotes":17005,"postalVotes":99,"totalVotes":17104,"percentage":11.13,"isLeading":false},{"rank":4,"name":"NOTA","party":"NOTA","evmVotes":1109,"postalVotes":6,"totalVotes":1115,"percentage":0.73,"isLeading":false},{"rank":5,"name":"RAJEEV K S","party":"AAP","evmVotes":1020,"postalVotes":15,"totalVotes":1035,"percentage":0.67,"isLeading":false}],"totalVotesCounted":153735,"round":"","lastUpdated":"at 12:42 AM On 05/05/2026"}