{"id":77,"name":"KALAMASSERY","district":"Palakkad","candidates":[{"rank":1,"name":"ADV. V E ABDUL GAFOOR","party":"IUML","evmVotes":79661,"postalVotes":945,"totalVotes":80606,"percentage":49.35,"isLeading":true},{"rank":2,"name":"P RAJEEVE","party":"CPI(M)","evmVotes":63413,"postalVotes":881,"totalVotes":64294,"percentage":39.36,"isLeading":false},{"rank":3,"name":"BINU","party":"BDJS","evmVotes":13981,"postalVotes":149,"totalVotes":14130,"percentage":8.65,"isLeading":false},{"rank":4,"name":"AJMAL K MUJEEB","party":"SDPOI","evmVotes":1572,"postalVotes":6,"totalVotes":1578,"percentage":0.97,"isLeading":false},{"rank":5,"name":"NOTA","party":"NOTA","evmVotes":1300,"postalVotes":19,"totalVotes":1319,"percentage":0.81,"isLeading":false},{"rank":6,"name":"SHAMSU T K","party":"AAP","evmVotes":544,"postalVotes":9,"totalVotes":553,"percentage":0.34,"isLeading":false},{"rank":7,"name":"SIYAD V A","party":"BSP","evmVotes":327,"postalVotes":4,"totalVotes":331,"percentage":0.2,"isLeading":false},{"rank":8,"name":"A RAJEENA","party":"SUCOI(","evmVotes":299,"postalVotes":2,"totalVotes":301,"percentage":0.18,"isLeading":false},{"rank":9,"name":"RAJEEV S/O VAREED","party":"IND","evmVotes":228,"postalVotes":5,"totalVotes":233,"percentage":0.14,"isLeading":false}],"totalVotesCounted":163345,"round":"","lastUpdated":"at 12:42 AM On 05/05/2026"}