{"id":235,"name":"KESHPUR","district":"Paschim Medinipur","candidates":[{"rank":1,"name":"SEULI SAHA","party":"TMC","evmVotes":142633,"postalVotes":490,"totalVotes":143123,"percentage":56.36,"isLeading":true},{"rank":2,"name":"SUVENDU SAMANTA","party":"BJP","evmVotes":92591,"postalVotes":427,"totalVotes":93018,"percentage":36.63,"isLeading":false},{"rank":3,"name":"GURUPADA MONDAL","party":"CPI(M)","evmVotes":10358,"postalVotes":74,"totalVotes":10432,"percentage":4.11,"isLeading":false},{"rank":4,"name":"KAMAL KISHOR","party":"INC","evmVotes":1829,"postalVotes":7,"totalVotes":1836,"percentage":0.72,"isLeading":false},{"rank":5,"name":"AJOY DOME","party":"IND","evmVotes":1832,"postalVotes":0,"totalVotes":1832,"percentage":0.72,"isLeading":false},{"rank":6,"name":"HARADHAN SING","party":"SUCOI(","evmVotes":1552,"postalVotes":8,"totalVotes":1560,"percentage":0.61,"isLeading":false},{"rank":7,"name":"NOTA","party":"NOTA","evmVotes":1541,"postalVotes":12,"totalVotes":1553,"percentage":0.61,"isLeading":false},{"rank":8,"name":"ARUN KARAN","party":"IND","evmVotes":608,"postalVotes":1,"totalVotes":609,"percentage":0.24,"isLeading":false}],"totalVotesCounted":253963,"round":"","lastUpdated":"at 01:30 AM On 05/05/2026"}