{"id":246,"name":"RAGHUNATHPUR","district":"Paschim Medinipur","candidates":[{"rank":1,"name":"MAMONI BAURI","party":"BJP","evmVotes":126532,"postalVotes":1096,"totalVotes":127628,"percentage":54.44,"isLeading":true},{"rank":2,"name":"HAZARI BOURI","party":"TMC","evmVotes":83110,"postalVotes":459,"totalVotes":83569,"percentage":35.65,"isLeading":false},{"rank":3,"name":"GANESH BOURI","party":"CPI(M)","evmVotes":10589,"postalVotes":96,"totalVotes":10685,"percentage":4.56,"isLeading":false},{"rank":4,"name":"NOTA","party":"NOTA","evmVotes":3176,"postalVotes":25,"totalVotes":3201,"percentage":1.37,"isLeading":false},{"rank":5,"name":"SANDHYA BAURI","party":"INC","evmVotes":3044,"postalVotes":21,"totalVotes":3065,"percentage":1.31,"isLeading":false},{"rank":6,"name":"ANIL BAURI","party":"SUCOI(","evmVotes":2498,"postalVotes":16,"totalVotes":2514,"percentage":1.07,"isLeading":false},{"rank":7,"name":"DHARANI DHAR BAURI","party":"IND","evmVotes":1375,"postalVotes":3,"totalVotes":1378,"percentage":0.59,"isLeading":false},{"rank":8,"name":"MAHADEB BAURI","party":"BSP","evmVotes":1194,"postalVotes":11,"totalVotes":1205,"percentage":0.51,"isLeading":false},{"rank":9,"name":"MAMANI BOURI","party":"IND","evmVotes":1181,"postalVotes":5,"totalVotes":1186,"percentage":0.51,"isLeading":false}],"totalVotesCounted":234431,"round":"","lastUpdated":"at 01:30 AM On 05/05/2026"}