{"id":285,"name":"SURI","district":"Paschim Bardhaman","candidates":[{"rank":1,"name":"JAGANNATH CHATTOPADHYAY","party":"BJP","evmVotes":122617,"postalVotes":1626,"totalVotes":124243,"percentage":52.09,"isLeading":true},{"rank":2,"name":"UJJAL CHATTERJEE","party":"TMC","evmVotes":94840,"postalVotes":717,"totalVotes":95557,"percentage":40.07,"isLeading":false},{"rank":3,"name":"MOTIUR RAHAMAN","party":"CPI(M)","evmVotes":7982,"postalVotes":82,"totalVotes":8064,"percentage":3.38,"isLeading":false},{"rank":4,"name":"ADHIKARI SANJOY","party":"INC","evmVotes":2654,"postalVotes":20,"totalVotes":2674,"percentage":1.12,"isLeading":false},{"rank":5,"name":"SEKH DALIM","party":"IND","evmVotes":1834,"postalVotes":1,"totalVotes":1835,"percentage":0.77,"isLeading":false},{"rank":6,"name":"NOTA","party":"NOTA","evmVotes":1817,"postalVotes":15,"totalVotes":1832,"percentage":0.77,"isLeading":false},{"rank":7,"name":"RAJINA KHATUN","party":"IND","evmVotes":1627,"postalVotes":4,"totalVotes":1631,"percentage":0.68,"isLeading":false},{"rank":8,"name":"BHASKAR DAS","party":"BSP","evmVotes":868,"postalVotes":4,"totalVotes":872,"percentage":0.37,"isLeading":false},{"rank":9,"name":"MONIR HOSSAIN KHAN","party":"IND","evmVotes":631,"postalVotes":7,"totalVotes":638,"percentage":0.27,"isLeading":false},{"rank":10,"name":"KOHINUR KHATUN","party":"AJUP","evmVotes":392,"postalVotes":2,"totalVotes":394,"percentage":0.17,"isLeading":false},{"rank":11,"name":"JINNATUL KHAN","party":"IND","evmVotes":382,"postalVotes":4,"totalVotes":386,"percentage":0.16,"isLeading":false},{"rank":12,"name":"NITAI ANKUR","party":"SUCOI(","evmVotes":229,"postalVotes":1,"totalVotes":230,"percentage":0.1,"isLeading":false},{"rank":13,"name":"AVISHEK CHAKRABORTY","party":"IND","evmVotes":146,"postalVotes":2,"totalVotes":148,"percentage":0.06,"isLeading":false}],"totalVotesCounted":238504,"round":"","lastUpdated":"at 01:30 AM On 05/05/2026"}