{"id":109,"name":"HOWRAGHAT","district":"Sibasagar","candidates":[{"rank":1,"name":"LUNSING TERON","party":"BJP","evmVotes":105526,"postalVotes":703,"totalVotes":106229,"percentage":68.23,"isLeading":true},{"rank":2,"name":"SANJEEB TERON","party":"INC","evmVotes":27943,"postalVotes":180,"totalVotes":28123,"percentage":18.06,"isLeading":false},{"rank":3,"name":"SARKIRI RONGPHAR","party":"IND","evmVotes":14595,"postalVotes":64,"totalVotes":14659,"percentage":9.42,"isLeading":false},{"rank":4,"name":"NOTA","party":"NOTA","evmVotes":2287,"postalVotes":35,"totalVotes":2322,"percentage":1.49,"isLeading":false},{"rank":5,"name":"RAJEN TIMUNG","party":"IND","evmVotes":1937,"postalVotes":6,"totalVotes":1943,"percentage":1.25,"isLeading":false},{"rank":6,"name":"RABI KUMAR PHANGCHO","party":"CPI","evmVotes":1403,"postalVotes":11,"totalVotes":1414,"percentage":0.91,"isLeading":false},{"rank":7,"name":"RABINDRA RONGPI","party":"IND","evmVotes":994,"postalVotes":6,"totalVotes":1000,"percentage":0.64,"isLeading":false}],"totalVotesCounted":155690,"round":"","lastUpdated":"at 02:09 AM On 05/05/2026"}