{"id":12,"name":"JALESHWAR","district":"Dhubri","candidates":[{"rank":1,"name":"AFTAB UDDIN MOLLAH","party":"INC","evmVotes":161941,"postalVotes":233,"totalVotes":162174,"percentage":69.19,"isLeading":true},{"rank":2,"name":"SHEIKH SHAH ALAM","party":"AIUDF","evmVotes":52353,"postalVotes":133,"totalVotes":52486,"percentage":22.39,"isLeading":false},{"rank":3,"name":"ABU SHA SHADI HOSSAIN","party":"AGP","evmVotes":12892,"postalVotes":62,"totalVotes":12954,"percentage":5.53,"isLeading":false},{"rank":4,"name":"SAHAB UDDIN AHMED","party":"IND","evmVotes":1831,"postalVotes":8,"totalVotes":1839,"percentage":0.78,"isLeading":false},{"rank":5,"name":"ARIF AKHTAR AHMED","party":"TMC","evmVotes":1766,"postalVotes":10,"totalVotes":1776,"percentage":0.76,"isLeading":false},{"rank":6,"name":"SAIFUL ISLAM","party":"SUCOI(","evmVotes":1287,"postalVotes":9,"totalVotes":1296,"percentage":0.55,"isLeading":false},{"rank":7,"name":"NOTA","party":"NOTA","evmVotes":1276,"postalVotes":10,"totalVotes":1286,"percentage":0.55,"isLeading":false},{"rank":8,"name":"DELOWAR HUSSAIN","party":"IND","evmVotes":565,"postalVotes":3,"totalVotes":568,"percentage":0.24,"isLeading":false}],"totalVotesCounted":234379,"round":"","lastUpdated":"at 02:09 AM On 05/05/2026"}