{"id":23,"name":"CHENGA","district":"Bongaigaon","candidates":[{"rank":1,"name":"ABDUR RAHIM AHMED","party":"INC","evmVotes":139005,"postalVotes":162,"totalVotes":139167,"percentage":56.85,"isLeading":true},{"rank":2,"name":"ASHRAFUL HUSSAIN","party":"AIUDF","evmVotes":51680,"postalVotes":138,"totalVotes":51818,"percentage":21.17,"isLeading":false},{"rank":3,"name":"AFTADUR ALI KHAN","party":"IND","evmVotes":43950,"postalVotes":71,"totalVotes":44021,"percentage":17.98,"isLeading":false},{"rank":4,"name":"SADDAM HUSSAIN","party":"AGP","evmVotes":5840,"postalVotes":39,"totalVotes":5879,"percentage":2.4,"isLeading":false},{"rank":5,"name":"NOTA","party":"NOTA","evmVotes":1842,"postalVotes":13,"totalVotes":1855,"percentage":0.76,"isLeading":false},{"rank":6,"name":"ABDUL RAHMAN","party":"IND","evmVotes":1437,"postalVotes":3,"totalVotes":1440,"percentage":0.59,"isLeading":false},{"rank":7,"name":"JOHIRUL ISLAM","party":"SUCOI(","evmVotes":636,"postalVotes":1,"totalVotes":637,"percentage":0.26,"isLeading":false}],"totalVotesCounted":244817,"round":"","lastUpdated":"at 02:06 AM On 05/05/2026"}