{"id":30,"name":"HAJO-SUALKUCHI","district":"Barpeta","candidates":[{"rank":1,"name":"PRAKASH CHANDRA DAS","party":"AGP","evmVotes":81077,"postalVotes":622,"totalVotes":81699,"percentage":47.84,"isLeading":true},{"rank":2,"name":"NANDITA DAS","party":"INC","evmVotes":80663,"postalVotes":312,"totalVotes":80975,"percentage":47.41,"isLeading":false},{"rank":3,"name":"ROJY AHMED","party":"TMC","evmVotes":2739,"postalVotes":29,"totalVotes":2768,"percentage":1.62,"isLeading":false},{"rank":4,"name":"NOTA","party":"NOTA","evmVotes":2368,"postalVotes":22,"totalVotes":2390,"percentage":1.4,"isLeading":false},{"rank":5,"name":"RAJU PATOWARY","party":"IND","evmVotes":2004,"postalVotes":21,"totalVotes":2025,"percentage":1.19,"isLeading":false},{"rank":6,"name":"SIDDHARTHA DAS","party":"IND","evmVotes":915,"postalVotes":14,"totalVotes":929,"percentage":0.54,"isLeading":false}],"totalVotesCounted":170786,"round":"","lastUpdated":"at 02:09 AM On 05/05/2026"}